helax/__init__.py
helax/diagrams.py
helax/jax/__init__.py
helax/jax/amplitudes.py
helax/jax/ampltidues_test.py
helax/jax/lvector.py
helax/jax/phase_space.py
helax/jax/testdata/spinor_data.npy
helax/jax/testdata/spinor_data.npz
helax/jax/testdata/spinor_test_data.npz
helax/jax/testdata/spinor_u.py
helax/jax/testdata/spinor_ubar.py
helax/jax/testdata/spinor_v.py
helax/jax/testdata/spinor_vbar.py
helax/jax/testdata/vector_wf_data.npz
helax/jax/testdata/vector_wf_test_data.npz
helax/jax/utils.py
helax/jax/wavefunctions.py
helax/jax/wavefunctions_test.py
helax/numpy/__init__.py
helax/numpy/amplitudes/__init__.py
helax/numpy/amplitudes/ffs.py
helax/numpy/amplitudes/ffs_test.py
helax/numpy/amplitudes/ffv.py
helax/numpy/amplitudes/ffv_test.py
helax/numpy/amplitudes/propagators.py
helax/numpy/amplitudes/wws.py
helax/numpy/amplitudes/wwv.py
helax/numpy/dirac.py
helax/numpy/helas.py
helax/numpy/lvector.py
helax/numpy/phase_space.py
helax/numpy/typing.py
helax/numpy/utils.py
helax/numpy/wavefunctions/__init__.py
helax/numpy/wavefunctions/dirac.py
helax/numpy/wavefunctions/dirac_test.py
helax/numpy/wavefunctions/scalar.py
helax/numpy/wavefunctions/testdata/spinor_data.npz
helax/numpy/wavefunctions/testdata/vector_wf_data.npz
helax/numpy/wavefunctions/utils.py
helax/numpy/wavefunctions/vector.py
helax/numpy/wavefunctions/vector_test.py
helax/numpy/wavefunctions/wely_test.py
helax/numpy/wavefunctions/weyl.py
helax/vertices.py
helax-0.1.4.dist-info/WHEEL
helax-0.1.4.dist-info/METADATA
helax-0.1.4.dist-info/RECORD
